README.md
setup.py
scrapy_rowspan_colspan_contents_copied/__init__.py
scrapy_rowspan_colspan_contents_copied/expand_colspan_rowspan.py
scrapy_rowspan_colspan_contents_copied/main.py
scrapy_rowspan_colspan_contents_copied.egg-info/PKG-INFO
scrapy_rowspan_colspan_contents_copied.egg-info/SOURCES.txt
scrapy_rowspan_colspan_contents_copied.egg-info/dependency_links.txt
scrapy_rowspan_colspan_contents_copied.egg-info/top_level.txt